src/__init__.py
src/cli.py
src/server.py
src/mail_service/__init__.py
src/mail_service/mail_service.py
aiden_mail-0.1.9.dist-info/METADATA
aiden_mail-0.1.9.dist-info/WHEEL
aiden_mail-0.1.9.dist-info/entry_points.txt
aiden_mail-0.1.9.dist-info/licenses/LICENSE
aiden_mail-0.1.9.dist-info/RECORD
