Metadata-Version: 2.4
Name: aiden-mail
Version: 0.1.9
Summary: An email MCP server with IMAP and SMTP support
Author-email: Huang Han <huanghan@foxwallet.com>
License-File: LICENSE
Requires-Python: >=3.13
Requires-Dist: email-validator>=2.0.0
Requires-Dist: fastmcp>=2.10.5
